synclub_mcp/__init__.py
synclub_mcp/__main__.py
synclub_mcp/client.py
synclub_mcp/const.py
synclub_mcp/exceptions.py
synclub_mcp/server.py
synclub_mcp/utils.py
synclub_mcp-0.7.9.dist-info/licenses/LICENSE
synclub_mcp-0.7.9.dist-info/METADATA
synclub_mcp-0.7.9.dist-info/WHEEL
synclub_mcp-0.7.9.dist-info/entry_points.txt
synclub_mcp-0.7.9.dist-info/top_level.txt
synclub_mcp-0.7.9.dist-info/RECORD
